MANIFEST.in
setup.py
citadel/__init__.py
citadel/admin.py
citadel/fields.py
citadel/models.py
citadel/tests.py
citadel/types.py
django_citadel.egg-info/PKG-INFO
django_citadel.egg-info/SOURCES.txt
django_citadel.egg-info/dependency_links.txt
django_citadel.egg-info/requires.txt
django_citadel.egg-info/top_level.txt