Metadata-Version: 1.0
Name: django-citadel
Version: 1.0.1
Summary: A Django app that provides an encrypted Model and ModelField
Home-page: https://github.com/mypetyak/django-citadel
Author: Christopher Bunn
Author-email: UNKNOWN
License: UNKNOWN
Platform: UNKNOWN
